Ungrabber/__init__.py
Ungrabber/classes.py
Ungrabber/cli.py
Ungrabber/extract.py
Ungrabber/main.py
Ungrabber/regs.py
Ungrabber/utils.py
Ungrabber/methods/Any.py
Ungrabber/methods/BlankGrabber.py
Ungrabber/methods/Empyrean.py
Ungrabber/methods/ExelaV2.py
Ungrabber/methods/Pysilon.py
Ungrabber/methods/RedTigerStealer.py
Ungrabber/methods/TrapStealer.py
Ungrabber/methods/__init__.py
Ungrabber/methods/example.py
Ungrabber/yara/rules.yar
ungrabber-0.0.7.dist-info/LICENSE
ungrabber-0.0.7.dist-info/METADATA
ungrabber-0.0.7.dist-info/WHEEL
ungrabber-0.0.7.dist-info/entry_points.txt
ungrabber-0.0.7.dist-info/top_level.txt
ungrabber-0.0.7.dist-info/RECORD
